esf_convert/__init__.py
esf_convert/cli.py
esf_convert-1.1.0.dist-info/METADATA
esf_convert-1.1.0.dist-info/WHEEL
esf_convert-1.1.0.dist-info/entry_points.txt
esf_convert-1.1.0.dist-info/licenses/LICENSE
esf_convert-1.1.0.dist-info/RECORD
