Metadata-Version: 2.4
Name: esf-convert
Version: 1.1.0
Summary: Convert ECHO Single Form (ESF) XML files to Markdown or Word documents
Project-URL: Homepage, https://github.com/brianmcdonald/esf-convert
Project-URL: Repository, https://github.com/brianmcdonald/esf-convert
Author: Brian
License-Expression: MIT
License-File: LICENSE
Keywords: converter,docx,echo,esf,humanitarian,markdown,xml
Classifier: Development Status :: 4 - Beta
Classifier: Environment :: Console
Classifier: Intended Audience :: End Users/Desktop
Classifier: License :: OSI Approved :: MIT License
Classifier: Operating System :: OS Independent
Classifier: Programming Language :: Python :: 3
Classifier: Programming Language :: Python :: 3.10
Classifier: Programming Language :: Python :: 3.11
Classifier: Programming Language :: Python :: 3.12
Classifier: Topic :: Text Processing :: Markup
Classifier: Topic :: Utilities
Requires-Python: >=3.10
Requires-Dist: lxml>=5.0.0
Requires-Dist: python-docx>=1.1.0
